{"ordenestot":[{"ordenestot":{"HC":"542233","NRO_SOLICITUD":"02840532","RECEPCION":"07\/12\/2020 06:00","ESTADO":"TOTAL","nombre":"","apellido1":"","apellido2":""}},{"ordenestot":{"HC":"542233","NRO_SOLICITUD":"02840309","RECEPCION":"05\/12\/2020 09:27","ESTADO":"TOTAL","nombre":"","apellido1":"","apellido2":""}},{"ordenestot":{"HC":"542233","NRO_SOLICITUD":"02840259","RECEPCION":"05\/12\/2020 04:00","ESTADO":"TOTAL","nombre":"","apellido1":"","apellido2":""}},{"ordenestot":{"HC":"542233","NRO_SOLICITUD":"02839598","RECEPCION":"04\/12\/2020 04:00","ESTADO":"TOTAL","nombre":"","apellido1":"","apellido2":""}},{"ordenestot":{"HC":"542233","NRO_SOLICITUD":"02839595","RECEPCION":"03\/12\/2020 20:58","ESTADO":"TOTAL","nombre":"","apellido1":"","apellido2":""}},{"ordenestot":{"HC":"542233","NRO_SOLICITUD":"02839478","RECEPCION":"03\/12\/2020 16:36","ESTADO":"TOTAL","nombre":"","apellido1":"","apellido2":""}}],"0":352}